colight_site/__init__.py
colight_site/builder.py
colight_site/cli.py
colight_site/executor.py
colight_site/generator.py
colight_site/parser.py
colight_site/watcher.py
colight_site-2025.4.1.dist-info/METADATA
colight_site-2025.4.1.dist-info/WHEEL
colight_site-2025.4.1.dist-info/entry_points.txt
colight_site-2025.4.1.dist-info/RECORD
